resolver/__init__.py
resolver/minify_file_contents.py
sceptre_minify_file_contents_resolver-0.1.7.dist-info/METADATA
sceptre_minify_file_contents_resolver-0.1.7.dist-info/WHEEL
sceptre_minify_file_contents_resolver-0.1.7.dist-info/entry_points.txt
sceptre_minify_file_contents_resolver-0.1.7.dist-info/top_level.txt
sceptre_minify_file_contents_resolver-0.1.7.dist-info/RECORD
