Metadata-Version: 2.1
Name: sceptre-minify-file-contents-resolver
Version: 0.1.7
Summary: Read and minify file contents
Home-page: https://github.com/sceptre/sceptre-minify-file-contents-resolver
Author: Mitchell Rowling
Author-email: mitchell.rowling@foxsports.com.au
License: Apache2
Keywords: sceptre,sceptre-resolver
Platform: UNKNOWN
Classifier: Intended Audience :: Developers
Classifier: Natural Language :: English
Classifier: Environment :: Console
Classifier: Programming Language :: Python :: 2.7
Classifier: Programming Language :: Python :: 3.5
Classifier: Programming Language :: Python :: 3.6
Classifier: Programming Language :: Python :: 3.7
Requires-Dist: packaging (==16.8)
Provides-Extra: test
Requires-Dist: pytest (>=3.2) ; extra == 'test'
